actuarialib/__init__.py
actuarialib/linearregression_model.py
actuarialib-0.1.1.dist-info/licenses/LICENSE
actuarialib-0.1.1.dist-info/METADATA
actuarialib-0.1.1.dist-info/WHEEL
actuarialib-0.1.1.dist-info/top_level.txt
actuarialib-0.1.1.dist-info/RECORD
